[
  {
    "name": "Комп'ютер Artline Gaming X51",
    "price": 28199,
    "description": "Персональні комп'ютери серії Artline Gaming — це комп'ютери для тих, хто любить і хоче відпочивати! ",
    "code": 273,
    "category": {
      "id": 1,
      "name": "Комп'ютери та ноутбуки"
    }
  },
  {
    "name": "Мобільний телефон Apple iPhone 13 128GB Starlight",
    "price": 32999,
    "description": "Передова система двох камер 12 Мп: ширококутна й надширококутна; Стилі фотографій, режим Smart HDR 4, Нічний режим, зйомка HDR-відео 4K у стандарті Dolby Vision",
    "code": 472,
    "category": {
      "id": 2,
      "name": "Смартфони, ТВ і Електроніка"
    }
  },
  {
    "name": "Ноутбук Lenovo IdeaPad Gaming 3 15IHU6",
    "price": 29999,
    "description": "Новітня відеокарта NVIDIA GeForce RTX серії 30 і продуктивний процесор Intel Core 11-го покоління, встановлений у максимальній конфігурації цього ноутбука, подбають, щоб твій ігровий потенціал сягнув нового рівня.",
    "code": 580,
    "category": {
      "id": 3,
      "name": "Товари для геймерів"
    }
  },
  {
    "name": "Пральна машина Samsung",
    "price": 12999,
    "description": "солоджуйтеся підвищеною енергоефективністю, зниженим рівнем шуму та тривалістю роботи. У технології цифрового інвертора використовують сильні магніти, що збільшують потужність. Але такий пристрій працює тихше й споживає менше енергії, ніж універсальний електродвигун. На нього також надають 10-річну гарантію.",
    "code": 898,
    "category": {
      "id": 4,
      "name": "Побутова техніка"
    }
  },
  {
    "name": "test",
    "price": 83887,
    "description": "test",
    "code": 895,
    "category": {
      "id": 10,
      "name": "test2"
    }
  },
  {
    "name": "test2",
    "price": 83887,
    "description": "test2",
    "code": 894,
    "category": {
      "id": 10,
      "name": "test2"
    }
  },
 {
    "name": "test3",
    "price": 8383,
    "description": "test3",
    "code": 890,
   "category": {
     "id": 10,
     "name": "test2"
   }
 },
  {
    "name": "test4",
    "price": 8383,
    "description": "test4",
    "code": 978,
    "category": {
      "id": 24,
      "name": "testCategory18"
    }
  },
  {
    "name": "ProductTest5",
    "price": 8383,
    "description": "testDescription5",
    "code": 977,
    "category": {
      "id": 23,
      "name": "testCategory17"
    }
  }
]